helm_package/__init__.py
helm_package/bin/macos/helm2
helm_package/bin/macos/helm3
helm_package/bin/windows/helm2.exe
helm_package/bin/windows/helm3.exe
helm_package-0.0.7.dist-info/LICENSE
helm_package-0.0.7.dist-info/METADATA
helm_package-0.0.7.dist-info/WHEEL
helm_package-0.0.7.dist-info/top_level.txt
helm_package-0.0.7.dist-info/RECORD
