Metadata-Version: 2.1
Name: helm-package
Version: 0.0.7
Summary: helm bin package for wins and macos including helm2 and helm3
Home-page: https://github.com/pypa/helm_bin
Author: tinson
Author-email: tinson.liu@6317.io
License: UNKNOWN
Project-URL: Bug Tracker, https://github.com/pypa/helm_bin/issues
Platform: UNKNOWN
Classifier: Programming Language :: Python :: 3
Classifier: License :: OSI Approved :: MIT License
Classifier: Operating System :: OS Independent
Requires-Python: >=3.6
License-File: LICENSE
